BitcoinPy/__init__.py
BitcoinPy/models/Block.py
BitcoinPy/models/BlockHeader.py
BitcoinPy/models/BlockchainParser.py
BitcoinPy/models/Mempool.py
BitcoinPy/models/Transaction.py
BitcoinPy/models/TransactionInput.py
BitcoinPy/models/TransactionOutput.py
BitcoinPy/models/TransactionWitness.py
BitcoinPy/models/__init__.py
BitcoinPy/tests/__init__.py
BitcoinPy/utils/__init__.py
BitcoinPy/utils/block_util.py
BitcoinPy/utils/opcodes.py
GraphBTC-1.1.dist-info/METADATA
GraphBTC-1.1.dist-info/WHEEL
GraphBTC-1.1.dist-info/top_level.txt
GraphBTC-1.1.dist-info/RECORD
