Metadata-Version: 2.1
Name: GraphBTC
Version: 1.1
Summary: Python package containing Bitcoin utilities including blockchain parser, script deciphering, and others
Home-page: https://github.com/markbentivegna/BitcoinPy
Author: Mark Bentivegna
Author-email: markbentivegna@gmail.com
Classifier: Programming Language :: Python :: 3
Classifier: License :: OSI Approved :: MIT License
Classifier: Operating System :: OS Independent
